<?xml version="1.0" encoding="UTF-8" standalone="no"?>
<pk><wd nm="efault_from" rd="54,0:10570"/><wd nm="efault_to" rd="54,0:10752"/><wd nm="efaultaccesscontrol" rd="52,0:3995"/><wd nm="efaultcontext" rd="57,0:5888"/><wd nm="efaults" rd="26,0:15515"/><wd nm="efer" rd="2,0:1673,6432,8171|5,0:907|7,0:387|18,0:759|20,0:1410|21,0:603,1246|23,0:4355|24,0:644|25,0:6407|26,0:145,1905,3758,8658|27,0:3605,6980|29,0:3717|32,0:855|33,0:1676|36,0:431|38,0:3057,3335,3787,3979|44,0:20696|47,0:58|56,0:1376|57,0:1599|61,0:678"/><wd nm="eferable" rd="23,0:4612|26,0:3986|31,0:2996"/><wd nm="eference" rd="26,0:928,10903,11027|27,0:4429,6075,6589,8086|29,0:2016,2088|31,0:3980|43,0:322|59,0:9060"/><wd nm="eferenced" rd="8,0:6957|20,0:2543|25,0:5681|31,0:3541"/><wd nm="eferences" rd="27,0:2099|30,0:10063|38,0:101|46,4:1844|47,4:2384|48,4:921|49,4:2009|51,4:586|59,0:9125"/><wd nm="eferencing" rd="2,0:11027,13291,13702,16257,18845|26,0:851"/><wd nm="eferred" rd="7,0:125|20,0:1466|25,0:5329|40,0:608|44,0:252,534|54,0:15800"/><wd nm="eferring" rd="21,0:78,1264|44,0:15369"/><wd nm="efers" rd="2,0:4128,8707|14,0:4673|23,0:7632|25,0:57,677,772,1428|27,0:5577|30,0:401|42,0:600,2345|44,0:8404,12451|61,0:3185"/><wd nm="effect" rd="7,0:3604|8,0:1962,4404,4429|14,0:1809|23,0:10190|30,0:1562,1825,2984,3174,3495|40,0:5228,6669,9790,10626,10716|44,4:4645,5504,5534|54,0:15080|57,0:2027"/><wd nm="effects" rd="44,0:5614"/><wd nm="effec­tiveness" rd="42,0:3352"/><wd nm="efficiency" rd="14,0:781,1454|16,0:338|17,0:931"/><wd nm="efficient" rd="26,0:5641|30,0:13639"/><wd nm="efficiently" rd="17,0:566"/><wd nm="effort" rd="33,0:284,769|59,0:94"/><wd nm="efforts" rd="33,0:375"/><wd nm="efile" rd="2,0:4813,4946,9403,9545|57,0:2411,2514,3235"/><wd nm="efilter" rd="26,0:14030,14516,14610"/><wd nm="efine" rd="8,0:2174,2461|9,0:70|10,0:137,289|11,0:1243,1643,2018,5437,5796|12,0:1400,1451,1686,3508|13,0:1882,4143,4262,5450|19,0:135,372|21,16:287,1561,1904|23,0:4726,7282|25,0:1191,4169|26,0:4911,12137|27,0:576|32,0:70,788|33,0:810|35,0:433,998|36,0:141|37,0:184,213,244|40,0:97,700,1629,5455,9446|42,0:78,4333,10094,10973,11420,15771|44,0:566,2691,5076,5428,6847,7022,10486,11124,14181,14398,14466,18741,20311,20622,20821|46,0:537|47,0:1960|51,0:541|52,0:3573|54,0:9281|59,0:417"/><wd nm="efined" rd="0,0:91,4573|2,0:16339,18927|6,0:286,358|7,0:1196,2519,3516,3844,3992,4802|8,0:1688,2371,2782,3494,4000|11,0:1870,4724|12,0:2087,2832|13,0:1117,5331,6882|15,0:577,804,1080,1378|20,0:602,903,2238|21,0:469,2448|23,0:349,7858|24,0:560|25,0:4844|26,0:2682,6547,7221,10032,10218,10295,11979,16937,17813|27,0:514,1524,2251,9284|29,0:387,1413|30,0:9806|33,0:70|35,0:221|36,0:339|40,0:7108|42,0:913,1794,2630,7361,8949,9187,10020,11828,12202,17881,17916|44,0:646,1891,2539,3697,5193,12194,12226,12516,18084,18224,19127,20437,20490|46,0:406|47,0:224,329,1665,2181|49,0:110,836|51,0:252|54,0:16479,17237,17574,17667|59,0:193,6558,9049,9580,10146|61,0:3316"/><wd nm="efines" rd="8,0:194|13,0:5372|42,0:12786|53,0:3616|54,0:17179,17316"/><wd nm="efining" rd="7,0:3386,3768|10,129:0,24,85,443|11,2:95,2584,4517,5155,5332|12,2:105,1337,2618,3392|13,0:566,1214|21,0:2577|23,0:2647,7153|27,0:9399|30,0:840|32,0:438|33,0:89|35,0:132|36,0:229,438|38,0:1609|39,0:337,548|40,4:1607|42,0:5400,14027|44,0:9549,19249|46,0:340|47,0:252|54,0:15884|61,0:10183|63,0:585"/><wd nm="efinitely" rd="19,0:2697|20,0:2158"/><wd nm="efinition" rd="7,0:1315|12,0:221|13,0:5132|19,2:1975,2042,2292,2357,2404,2475,2895,2940,2968,3012|20,0:218,628|23,0:2229,2309,6760,6968|25,0:1148,6558,7532|26,14:208,2929,7252,7268,8722,8998,9046,9246,9411,10421,10477,10758,10834,10912,10959,11036,11130,11179,11391,15447,16454,16505,16611,16674,16736,16793,18559,19100,19136,19264,19279,19324,19375,19411|27,0:1231,1800,1920,2123,2348,6087,6122,6279,6518,8130,10629,10699,10836|29,0:2994,5013,5511,5979,7016,7498,7654,7683,7747,7781,9581|30,0:1328,1546,1739,1895,2341,3109,3158,4019,4719,6418,10089,10423|38,0:473,514,723,764,1179,1378|44,4:4042,5479,10762|52,0:4725|54,0:12752,17356,17969"/><wd nm="efinitional" rd="44,0:4947"/><wd nm="efinitionfile" rd="26,0:8378|27,0:7143,7429,10601|29,16:3510,5912|30,16:5217,6814"/><wd nm="efinitions" rd="13,0:2743|15,0:702,722,4265|21,0:1135|23,0:7694|27,0:7929,8346|35,0:201|44,0:36,12498,15189,17994|52,0:6357|54,0:947,9189|59,0:6942,9179,9205,9386|63,0:893,1108"/><wd nm="efini­tion" rd="26,0:7644,11322"/><wd nm="efini­tions" rd="42,0:16002"/><wd nm="efin­ing" rd="40,0:1527"/><wd nm="efit" rd="14,0:1267|35,0:123|42,0:1981"/><wd nm="efix" rd="11,0:5029"/><wd nm="efi­nition" rd="33,0:758"/><wd nm="eflect" rd="11,0:2443|17,0:6490|60,0:194"/><wd nm="eflected" rd="42,0:4065|57,0:2388"/><wd nm="eflects" rd="39,0:1807|42,0:16383"/><wd nm="efore" rd="7,0:532,2268,3563|8,0:8489,8608,9412,9560,10080|12,0:466,756|15,0:5317|17,0:153,5822,8305|19,0:2266|21,0:794|23,0:10166|25,0:6848|27,2:3665,3681,3843,3898|29,0:2471,4838,6862|31,0:2135,3447|40,0:3497,4310,5196,11429|42,0:518,16038,16956|44,0:2153|52,0:147,507|53,0:3387|57,0:1999,3952,7221,7303|59,0:3176,7955,9148,10016,11161|61,0:2345,4993,7990,8756"/><wd nm="eforehand" rd="33,0:189"/><wd nm="eform" rd="8,0:5330"/><wd nm="efox" rd="39,0:803"/><wd nm="efrain" rd="59,0:10966"/><wd nm="efresh" rd="30,0:811"/><wd nm="efreshes" rd="30,0:11716"/><wd nm="efse" rd="38,0:3306|61,16:7126"/><wd nm="efse_status" rd="61,16:6581"/><wd nm="efse_stop" rd="38,0:3028|61,16:5509"/><wd nm="eft" rd="13,0:5362,5461|14,0:465|23,0:5817|26,0:5301,6605,18095|38,0:4862,5265,5526,5871,6176,6548|40,0:1778,7514|41,0:778,1166,1551,2358|42,0:9944,10170,14619,15114|44,0:2482,16283,20052|49,0:1254|54,0:10448,10559"/><wd nm="eftmost" rd="38,0:5682"/><wd nm="eful" rd="7,0:2171|11,0:1316|15,0:6520|17,0:8741|36,0:220|40,0:1995,5247|41,0:3457,4236,7697|42,0:5788|44,0:14626,16711|57,0:2558"/><wd nm="efused" rd="57,0:4847|59,16:2409,7096"/><wd nm="ef­inite" rd="33,0:848"/><wd nm="ef­inition" rd="23,0:3351|26,0:9119|30,0:989"/><wd nm="egacy" rd="44,0:13929"/><wd nm="egarding" rd="61,0:130"/><wd nm="egardless" rd="19,0:3566|25,0:4473|61,0:2156"/><wd nm="egard­less" rd="60,0:1250"/><wd nm="egate" rd="15,0:6241|42,0:13380"/><wd nm="egated" rd="54,0:15985,16783,16844"/><wd nm="egates" rd="20,0:6486"/><wd nm="egating" rd="42,0:13747"/><wd nm="egedit" rd="56,0:2366,3235,4565|60,0:1841"/><wd nm="egemot" rd="23,16:9058,9079"/><wd nm="egeneration" rd="16,0:391"/><wd nm="eger" rd="17,0:2534,3188,4565,5890,6289|26,0:18745,18855,19003,19188|56,0:1772"/><wd nm="egers" rd="26,0:16250"/><wd nm="eges" rd="13,0:3053|15,0:2315|20,0:3269|23,0:3802|26,0:3468|27,0:9954|42,0:4539|54,0:4986|59,0:3017,7799|61,0:6965"/><wd nm="egies" rd="33,0:1494"/><wd nm="egin" rd="2,16:2738,2821,7098,7181,12279,12362,15204,15287,17836,17919|15,0:4940|17,0:3449,5270,9030|26,0:16874|27,0:3852|30,0:13533|53,0:1002"/><wd nm="eginning" rd="17,0:2493,3844|21,0:1845|23,0:4790|26,0:18779,18889,19037,19222|57,0:6516"/><wd nm="egins" rd="26,0:12623|29,0:9271"/><wd nm="egional" rd="17,0:4123"/><wd nm="egister" rd="3,0:259|38,0:1524|40,0:7989|61,0:771"/><wd nm="egistered" rd="1,0:1804|7,0:3302,3614|15,0:521|54,0:16004,16309"/><wd nm="egistering" rd="7,0:4044|8,129:0,22,11409|9,0:300|54,2:981,15653,15825,16140,16343"/><wd nm="egisters" rd="2,0:10004|40,0:8037|54,0:16433"/><wd nm="egistration" rd="2,0:10430,10558|3,0:168|40,4:7760,8666|54,0:16097|56,0:5298|61,0:9680"/><wd nm="egistry" rd="56,0:2170,2285,2394,2931,2996,3154,3263,4368,4484,4593|60,0:1714,1760,1869"/><wd nm="egis­tration" rd="54,0:15812"/><wd nm="egories" rd="7,0:668|44,0:1410,10163,10361,14733|62,0:322"/><wd nm="egorize" rd="11,0:1405"/><wd nm="egory" rd="26,0:13552"/><wd nm="egrate" rd="53,0:3216"/><wd nm="egrated" rd="23,0:1723|42,0:5602"/><wd nm="egrates" rd="54,0:2187"/><wd nm="egration" rd="8,0:8853|53,0:3283"/><wd nm="egregate" rd="42,0:13380"/><wd nm="egregating" rd="42,0:13747"/><wd nm="egular" rd="1,0:1526|2,0:799|23,0:5918|25,0:1945|26,0:6706,18196|30,0:12119|45,0:191"/><wd nm="egy" rd="57,0:1960"/><wd nm="eg­istration" rd="2,0:10071"/><wd nm="ehand" rd="33,0:189"/><wd nm="ehandlers" rd="30,0:9830|38,0:4670|54,0:12435,12796"/><wd nm="ehave" rd="54,0:16471|59,0:6508"/><wd nm="ehaves" rd="40,0:10122|59,0:4755,9494"/><wd nm="ehavior" rd="11,0:2497|14,0:1043|17,0:1976,3233,5065|26,0:14157|39,0:416|40,0:307|41,0:7542|53,0:1890|54,0:169|56,0:1053,1144|59,0:9888"/><wd nm="ehaviors" rd="8,4:8337,9898|59,0:9770"/><wd nm="ehensive" rd="63,0:241"/><wd nm="ehind" rd="61,0:4427"/><wd nm="eicenet" rd="56,0:5668|61,0:10060"/><wd nm="eighs" rd="44,0:13430"/><wd nm="eight" rd="25,0:2687"/><wd nm="eindexed" rd="17,0:627"/><wd nm="eindexing" rd="14,0:929|17,0:1227,3223,3426,3667,3815,4220"/><wd nm="eindex­ing" rd="17,0:4369"/><wd nm="eing" rd="7,0:895|17,0:5828|23,0:3175,3514|25,0:751|26,0:11587|29,0:1247,7595|30,0:13579|33,0:1025,1208|38,0:6108|41,0:3619|44,0:19848|52,0:5612|54,0:1533,14291|59,0:10853|61,0:5043,8408,8803"/><wd nm="einstalled" rd="41,0:7797"/><wd nm="einterval" rd="14,0:1398|17,0:2177,2776|45,0:961"/><wd nm="ein­stalled" rd="61,0:8992"/><wd nm="eipaddress" rd="8,0:6079"/><wd nm="eir" rd="1,0:885|2,0:577,4388,8974|3,0:158|5,0:918|7,0:1942|8,0:3411|12,0:1808,3680|15,0:5906|17,0:8973|21,0:630|26,0:1607|27,0:420|30,0:9053|31,0:4587|40,0:3107,7671,11294,11585|41,0:1028,2085|42,0:3524,5159,5213,10828|44,0:4454,9464,10651,19339|49,0:482|53,0:3093|54,0:7654|56,0:665|58,0:235|59,0:688,3789,3937,4151,10817"/><wd nm="either" rd="7,0:2538|8,0:4159,10851|13,0:1918|14,0:1349|15,0:180,2673,6306|17,0:2930,3546,3576,5392,5422,7658|18,0:2730|23,0:6948|25,0:3032|26,0:421,10436,12938,13097,13249|27,0:130|29,0:2185|30,0:9399,11569|40,0:1098|41,0:6548|44,0:1032,3931,5844,8880,15271,18603|46,0:670|47,0:507,1305|53,0:3050|54,0:13832|55,0:297|56,0:2908|59,0:1336,4946|61,0:1886|62,0:112"/><wd nm="eive" rd="7,0:4271|8,0:9991|40,0:11207,11274,11552|61,0:3923,4197"/><wd nm="eived" rd="41,0:2077,2503,2728,2943,7392|57,0:4815|61,0:4262"/><wd nm="eiver" rd="1,0:157"/><wd nm="eives" rd="27,0:9196|40,0:4930|41,0:2842|61,0:4000"/><wd nm="ejungle" rd="46,16:1717|54,0:1625"/><wd nm="ejungle2" rd="23,16:6529,7056"/><wd nm="ek" rd="14,0:2894,3513|17,0:3483,3774,3808,3925,3938|18,0:413|20,0:1867|54,0:9147"/><wd nm="ekend" rd="8,0:6705"/><wd nm="ekendaccess" rd="8,16:7164"/></pk>