<?xml version="1.0" encoding="UTF-8" standalone="no"?>
<pk><wd nm="ec" rd="20,0:2447"/><wd nm="ecaqawfzelmakga1uebhmcvvmxczajbgnvbagtaknbmriweaydvqqhewltyw4gtwf0zw8xezarbgnvbaotckjsdwvkdw5nbguxhdaabgnvbaste0nvbxbsawfudevudgvychjpc2uxhdaa" rd="2,16:2853,7213,12394,15319,17951"/><wd nm="ecause" rd="2,0:4329,8915|5,0:851|8,0:3901,11025|14,0:829|16,0:300|17,0:8420|20,0:979|21,0:140|23,0:4318,7720|26,0:3721|29,0:4468,6502,7279,9973|30,0:260|33,0:518|39,0:649|40,0:8508|41,0:4242|42,0:6460|44,0:10476,13225,16102|46,0:783|49,0:915|50,0:143|53,0:3747|54,0:5745|57,0:7080|59,0:9758|61,0:3458"/><wd nm="ecaution" rd="35,0:641|40,0:1432"/><wd nm="ece" rd="15,0:4018|44,0:11740"/><wd nm="eceive" rd="7,0:4271|8,0:9991|40,0:11207,11274,11552|61,0:3923,4197"/><wd nm="eceived" rd="41,0:2077,2503,2728,2943,7392|57,0:4815|61,0:4262"/><wd nm="eceiver" rd="1,0:157"/><wd nm="eceives" rd="27,0:9196|40,0:4930|41,0:2842|61,0:4000"/><wd nm="ecember" rd="17,0:6787"/><wd nm="ecent" rd="14,0:1125,1487|41,0:2094"/><wd nm="ecently" rd="12,0:725,788|44,0:6111"/><wd nm="ecentralized" rd="12,0:1759"/><wd nm="eces" rd="44,0:3374"/><wd nm="ecessarily" rd="17,0:7597|40,0:7869|41,0:5666,7011|55,0:236|57,0:7245"/><wd nm="ecessary" rd="0,0:408|2,0:4320,8906|3,0:90|14,0:2835|26,0:15427,15650|27,0:6327|42,0:12669|44,0:3221|52,0:109|57,0:4523|60,0:739"/><wd nm="eces­sarily" rd="40,0:8590"/><wd nm="echanical" rd="33,0:274"/><wd nm="echanism" rd="7,0:1152|23,0:8162|42,0:12132|56,0:264"/><wd nm="echanisms" rd="14,0:2353"/><wd nm="echecking" rd="54,0:15642"/><wd nm="echnical" rd="56,0:952|57,0:302"/><wd nm="echnically" rd="13,0:133|23,0:270|26,0:4585|35,0:595|38,0:1480|44,0:16919|59,0:6370"/><wd nm="echnique" rd="42,0:1126"/><wd nm="echni­cal" rd="18,0:1616"/><wd nm="echni­cally" rd="26,0:10100|36,0:417"/><wd nm="ecial" rd="7,0:498,2911|8,0:4308|11,0:572|13,0:3299|19,0:463|20,0:1543,4639|25,0:7132|26,0:5673,14013|27,0:428|44,0:19207|54,0:1011,15779|59,0:8996|61,0:4650"/><wd nm="ecialized" rd="14,0:4350,4494|26,0:7633|44,0:52,3657"/><wd nm="ecially" rd="14,0:1205|23,0:3889|49,0:1678"/><wd nm="ecide" rd="40,0:5817,11076|61,0:1750"/><wd nm="ecides" rd="44,0:13498"/><wd nm="ecifi" rd="23,0:3843"/><wd nm="ecific" rd="7,0:4908|8,0:4759,6730|14,0:3808,4381|17,0:1687,2596,4073,6923|20,0:6833|23,0:5174,5386|26,0:5422,5816,6028,17151|27,0:5840|28,0:923|33,0:1460|40,0:7247|44,0:11446,11558,12027,12064,12176,13239,13709,13736|54,0:1032|63,0:1262"/><wd nm="ecifically" rd="7,0:445,2784|27,0:3533,3776|46,0:278|53,0:2922|59,0:921"/><wd nm="ecification" rd="26,0:12297|59,0:3862,5254"/><wd nm="ecifications" rd="59,0:3726"/><wd nm="ecified" rd="0,0:1086,1442,3402|2,0:16866|5,0:633|7,0:302,2983,3010|8,0:3262|11,0:1109,4119|12,0:1048|15,0:2103,2382|17,0:822,3469,3862,6722|18,0:2066,2202,2382,2544|19,0:624|20,0:2692|23,0:5313,5986|24,0:181|25,0:6245|26,0:5955,6521,6774,7195,8296,17020,17079,18264|27,0:3573,10207|29,0:5965,7796,9567|30,0:1676,1725,2001,3095,3144,5285,6859,10030,11614,12494|40,0:8128,8273,8337,8427,8518|42,0:3795,7525,7747,12603|44,0:2996,4301,6885,10998|52,0:2397|54,0:1862,4196,4364,6613,9860,10680,10861,12167,12738,17413|55,0:423|57,0:2947,3448,4336|59,0:2638,2901,3345,3895,4079,4273,4524,4807,4961,5228,7714,8128"/><wd nm="ecifier" rd="59,0:4050,4231,4427"/><wd nm="ecifies" rd="8,0:704,864|11,0:4369|12,0:2470|13,0:3514,3717|15,0:3323|17,0:2190,3006,3402,3785,4327,5219,5757,6039|18,0:1875,1948,2662,2778,2878,2969|21,0:326|23,0:3774,3961,4225,5908,9218,9284,9409,9568,9677,9852|26,0:3182,3265,3440,3634,4114,6696,14219,16474,18186|40,0:2179,2625,3803|54,0:1508,7782,8076,8306,8844,8987,9405,9752,9990,10233,10584,10764,10992,11128,11340,14988,15151,16702,16904,17093,17688,17842|57,0:2425,8429"/><wd nm="ecify" rd="0,0:1482,3006|2,0:448,19840,20958,20996|8,0:2239,3452,4875|11,0:4426|12,0:2527|13,0:4295,6287|17,0:4104,7095|23,0:3230,6627|26,0:541,2562,4773,11308,11348,16786,19250,19307|27,0:1944,8240|29,0:1768,3654,7869|30,0:1300,1438,2317,2432|40,0:1650,1889,3052,3370,6607,8898|42,0:6358,6936,14907|52,0:3738|54,0:4001,8463|59,0:2116,5322,6416,6482,9806,9866"/><wd nm="ecifying" rd="17,0:8702|19,0:1990|20,0:256|25,0:4263|26,0:12998,13145,13341,18601|36,0:529|59,0:6203|61,0:3642,3702"/><wd nm="ecipient" rd="8,0:6459|44,0:11007|54,0:10850,12727"/><wd nm="ecisely" rd="33,0:1183"/><wd nm="ecision" rd="8,0:5743,7910|44,4:13123,13297"/><wd nm="ecisions" rd="44,0:14328"/><wd nm="eci­fied" rd="30,0:4062|44,0:18629"/><wd nm="eck" rd="3,0:824|8,0:8778,8788,10298|13,0:6170,6756|15,4:5097|19,0:1478|20,0:3685|23,0:1715,1771|31,0:382,2810|38,0:1940,2553,2733,3530,4184,4765,4994,5161,5436,5674,5762,6308,6573|40,0:3670,5285|41,0:4869,5448,7360|42,0:6915,14685,17451,18367|44,0:5888|46,0:389|59,16:2416,2504,7103|61,0:1702,6415,6502"/><wd nm="eckbox" rd="8,0:629|23,0:1759"/><wd nm="ecked" rd="54,0:12263"/><wd nm="ecking" rd="27,0:7878|29,0:4246,6390|30,0:12015|31,2:225,308|44,0:591,5957|54,0:15573,15642"/><wd nm="eckout" rd="15,16:5045"/><wd nm="ecks" rd="7,0:2640|40,0:4975"/><wd nm="ecome" rd="7,0:3635|12,0:1939|14,0:3573|40,0:3448"/><wd nm="ecomes" rd="14,0:2488|17,0:6599|19,0:287"/><wd nm="ecommend" rd="27,0:9966|35,0:653|59,0:6400"/><wd nm="ecommended" rd="14,0:3528|17,0:4956,8543|18,0:598|30,0:12140|35,0:895|40,0:1364,2885,3213|57,0:1862,2661"/><wd nm="ecomputer" rd="8,0:5813"/><wd nm="ecom­mend" rd="49,0:976"/><wd nm="ecom­mended" rd="5,0:731"/><wd nm="econd" rd="8,0:5755,11230|11,0:2881|19,0:3843|20,0:5640|26,0:11097,14945|33,0:1347|42,0:12004|44,0:12408|48,0:819"/><wd nm="econdary" rd="44,0:16547|54,0:14651"/><wd nm="econdly" rd="26,0:2729"/><wd nm="econds" rd="17,0:2940,3556,5402|54,0:7806,8100,8330,8868,9429,10014,11016|57,0:4886"/><wd nm="econfiguration" rd="56,0:4999,5080"/><wd nm="econfigure" rd="57,0:2177|61,0:9414,9556"/><wd nm="econfigured" rd="48,0:295"/><wd nm="econfiguring" rd="61,2:300,9239|62,0:89"/><wd nm="econnect" rd="40,0:11448"/><wd nm="ecord" rd="8,0:8971"/><wd nm="ecorded" rd="25,0:6652"/><wd nm="ecords" rd="60,0:1614"/><wd nm="ecpath" rd="8,16:1570,1630,1670|54,0:17053"/><wd nm="ecrease" rd="15,0:4382"/><wd nm="ecreasing" rd="17,0:1823"/><wd nm="ecret" rd="3,0:762|56,0:5398"/><wd nm="ect" rd="0,0:880|2,0:458,3147,3181,3202,3225,7507,7541,7562,7585,12688,12722,12743,12766,15613,15647,15668,15691,16614,18245,18279,18300,18323|7,0:1293,3604,4381|8,0:1962,2857,3480,3987,4404,4429,4767,7556,9249,9983|11,0:2443|13,0:984|14,0:1809|15,4:211,2842,6442,6495,6540|17,0:6490|19,0:528|20,0:498,3145|23,0:673,1111,1354,1412,3814,8009,10190|24,0:497|25,0:6747|26,0:372,3233,3312,3490,13309,13591|27,0:776,4068,5706,6338|30,0:1562,1825,2864,2984,3174,3495|38,0:4244|39,0:730|40,0:2360,3182,4023,4421,5228,5503,6669,7493,7849,8612,9790,10626,10716,11398,11448|41,0:1991,5819,5866,6074,6312|42,0:7148,7200,7574,7863,8101,8513,8698,12252,15605,17132,17252,17293,17424|44,4:546,1315,2037,2912,3836,4530,4562,4645,4666,4829,5008,5504,5534,9769,10128,10195,10291,10574,10721,10960,13398,15333,15805,15859,16031,16518,18030,18559,18668,19517,19677,19760,19777,19915,20149|48,0:513|52,0:3165,3195,3218,3280,3329,3539,3633,3661,4624,4652,4764|53,0:1545,3573|54,0:10324,12583,13863,15080,17653|56,0:2249,3059,3134,3423,3688,3764,4078,4448|57,0:2027,2232,6543|59,0:1672,5916,6925,10575,10987|60,0:194|61,0:477,733,6195,8128,9486,9913,10150"/><wd nm="ectable" rd="8,0:4595"/><wd nm="ectangles" rd="23,0:2996|26,0:2181"/><wd nm="ectcategory" rd="26,0:13552"/><wd nm="ectclass" rd="26,16:4965,5013,10528,10595,13539|27,0:4009,4105"/><wd nm="ected" rd="8,0:639,2345,3131,7669,7836|11,0:2486|17,0:1904,4992|25,0:7098|38,0:5128,5458,5574|40,0:2299,2661,3574,5179,11253,11350|41,0:941,1809,1981,3029,4758,6136|42,0:4065,7540,7670,7708,17392|44,0:4995,10691,12051,14847,15065|54,0:12375|56,0:1690|57,0:2388,5454,7508|59,0:1004,1047"/><wd nm="ectguid" rd="27,0:4243"/><wd nm="ecting" rd="15,0:89|21,0:267,1605|23,0:4263|26,0:3672|40,0:1685,4532|41,0:2600|49,0:1221|52,0:4841|54,0:4817,13663"/><wd nm="ection" rd="1,0:1342,1533|2,0:758,4716,5217,9301,9826,19302,19457|7,0:3379,3726|8,0:130,184,2281,4118,4225,4503,5218|9,0:49|11,0:4215,4257,4324,4967|12,0:2317,2358,2425,3068|13,0:5201,5235|14,0:39|15,20:551,609,778,842,1054,1111,1352,1410,1432,1532,1546,1837,1951,2198,2637,2990,3277,3474,3508,3572,3629,3692,4250,4576,5054,5087,5131,5919,6184,6250,6374|17,0:1321,2068,3334,3493,5162|18,0:2846|19,0:2908|20,0:2328,2646,2743,3765,3863,6803,7175,7768,7802,7961|21,0:2175|23,0:174,1916,1965,2211,2331,2426,2825,2891,3088,3703,3912,4379,4492,4867,6747,6955,7365,7414|25,0:1367,6542,7516|26,14:192,273,289,558,770,875,1214,1479,1495,1543,2366,2402,2444,2591,2810,2918,3008,3067,3133,3782,3866,4492,4635,6419,7093,14702,15436,16969,17845,18915,18951,19073|27,4:967,1029,1081,1100,1173,1220,1365,1398,1430,1463,1772,1839,1867,2112,2176,2211,2239,2282,2330,2582,2756,2786,3074,3242,3587,6108,6294,6388,6507,8119,10338,10445,10582|28,0:470,564|29,6:53,162,302,515,670,1514,1563,1642,2028,2100,2279,2981,3631,3793,3839,7005,7927,9350|30,0:1341,1690,1882,2564,4706,5299,8028,9845,10102,10333,11644,12241,12623|31,0:3406|32,0:865|33,0:1608|34,0:47|38,0:19,455,705,1360,1533,4685|40,0:7676,9251|41,0:5298|42,0:547,1415,5329,17376|44,4:21,2786,2828,3612,4084,4390,6685,18921|45,0:294|46,0:1644|48,0:149,273,350,386,667,801,833,1066|52,0:307,1812,1864,2040,2090,2171,2229,4994|53,0:1211,1301,1499|54,0:1235,1285,3347,3603,3703,4388,6283,6445,6570,7379,7673,9235,10166,10384,10495,12450,12811,14773,14899,15874,15915,16123,16232,16275,16393,16410,16505,16526,17265,17290|55,0:41,645|56,0:2803|57,0:411,531,2506,2713,3959,4739,4935,5137,5161,5902,6053,6125,6361,6402,6638,6987,7046|59,16:2000,2399,2718,6224,7086,7539|61,0:584,5200"/><wd nm="ection_communication" rd="52,0:2187"/><wd nm="ection_desktop" rd="52,0:1828"/><wd nm="ection_email" rd="52,0:2056"/><wd nm="ection_file" rd="27,0:7123,7409,10300|29,16:3489|30,16:5197"/><wd nm="ectionpool" rd="15,0:1639,1823|48,0:401"/><wd nm="ectionpoolname" rd="15,0:1987"/><wd nm="ectionpools" rd="15,0:1803|48,0:335"/><wd nm="ections" rd="0,0:321|2,0:806|8,0:2252|10,0:198|15,0:286,354,1465,1654,2032,3128,3367,3544,3608,3669,3744,3777,4007,4772,4865,5279,5356,5479,5563,5678,5741|16,0:441|20,0:2294,7009|22,0:300|23,0:1488,1584,2379,8125|26,0:679|27,6:674,925,1294,2682,3308,6802,8070|28,0:642,853|29,0:341,6750|30,0:1183|42,0:17360|43,0:211|48,0:415|53,0:1351,1464,2972,3063|54,0:801,7234,7599,13938,14006,16561|55,0:679|57,0:887,1154,1260,1462,6242|59,0:1404|63,0:406"/></pk>