<?xml version="1.0" encoding="UTF-8" standalone="no"?>
<pk><wd nm="jectsid" rd="27,0:4384"/><wd nm="ject’s" rd="42,0:14126"/><wd nm="jedsharepoint" rd="23,16:8943"/><wd nm="jimmy" rd="46,16:1701"/><wd nm="jks" rd="0,16:936,1217,1723,2338,2863,3231,3517,3926,4425|1,0:496,570,1103,1125,1233,1255,1373,1395,1559,1581,1603,1643,1663,1908,1930,1977,2008,2154,2277,2299,2344|2,16:1854,1872,2192,2342,3655,3713,4026,4059,4855,4998,5130,5173,5579,5597,6212,6702,8012,8068,8227,8342,8439,8600,8638,9454,9602,9734,9777,10105,10127,10938,11006,11277,11299,11561,11876,13195,13258,13521,13606,13669,13914,14021,14366,14786,16174,16224,16394,16671,16789,17166,17422,18762,18812,18981,19131,19212,19774,20043,20063,20406,20562,20780,21076,21287,21451,21484|3,0:732,752|4,0:218,330,421|5,0:609|23,16:9047,9100,9631,9890|29,16:1354|56,0:5388,5435,5494|57,0:3214,3721|61,0:9727,9759"/><wd nm="job" rd="26,0:12497|54,0:11390,11432"/><wd nm="jobs" rd="45,0:1014"/><wd nm="joining" rd="54,0:6785"/><wd nm="jones" rd="8,16:7199"/><wd nm="jor" rd="44,0:3369,17422"/><wd nm="journal" rd="14,0:150,515,1790,1924,2097|15,0:867,886,1342,3658|16,0:159|17,0:181,539,868,1068,5809,6400,6528,6765,8821,8932|25,0:1289|40,0:11616|41,0:3347,3808|44,4:753,813,991,1010,1629,7595,8174,8872,10925,17061,17400,17574|48,0:134,261,458|54,0:9528,9627,13757,14224,14380"/><wd nm="journalsettingconfiguration" rd="17,0:1286,2019,5110|45,0:891,1065,1164"/><wd nm="jour­nal" rd="14,0:869|17,0:4769|56,0:705"/><wd nm="jour­nalsettingconfiguration" rd="17,0:3275"/><wd nm="jpc2uxhdaa" rd="2,16:2853,7213,12394,15319,17951"/><wd nm="jpg" rd="1,0:313|2,0:5194,9798|7,0:574|8,0:464,2900,5343,6852|11,0:5149|12,0:3287|13,0:502,5582|15,0:1760|17,0:751,2139,4586,6309|18,0:1234|19,0:1351,3002|20,0:3063,4009|21,0:648|23,0:2363,3681|24,0:588|25,0:6131|26,0:2345,9401,12202,15142,16284|27,0:2676|29,0:2261|32,0:902|35,0:1128|39,0:1582|40,0:144,914,7577,9992,10529|41,0:577,1373,5384|42,0:191,6320,9489,10185,11091,14270,18438|46,0:441,643|47,0:1507|48,0:1052|49,0:1970|52,0:3490,4015|53,0:1487|54,0:6388,12916|56,0:733,5680|59,0:2293,6325|61,0:2237,3636,4817,5394,10070"/><wd nm="jsdwvkdw5nbguxhdaabgnvbaste0nvbxbsawfudevudgvychjpc2uxhdaa" rd="2,16:2853,7213,12394,15319,17951"/><wd nm="jsk" rd="2,0:19742"/><wd nm="judge" rd="14,0:222"/><wd nm="judging" rd="41,0:3466"/><wd nm="junction" rd="59,0:4021,4202,4398"/><wd nm="jungle" rd="46,16:1717|54,0:1625"/><wd nm="jungle2" rd="23,16:6529,7056"/><wd nm="just" rd="14,0:1336|15,8:1480,1506,4207,4742|17,0:5330|19,0:2219,2311,3353|23,0:1435|25,0:4731|26,0:15920,18542|38,0:1494|40,0:7142,8504,9394|46,0:1530|59,0:5297"/><wd nm="justed" rd="30,0:8809"/><wd nm="justing" rd="15,4:3268"/><wd nm="jvm" rd="56,0:1922,2035|60,0:1685"/><wd nm="k" rd="2,0:19742,20025|3,0:824|7,0:1036,1567,2356|8,0:4694,5074,5292,8778,8788,8949,10298,10477,10692,10746,10795,11021,11256|11,0:1077,2958,3238,3518,6085|12,0:1475,1661|13,0:264,835,897,916,3685,3886,4092,5058,6170,6756|14,0:1639,2894,3427,3513,4027|15,4:816,1034,1139,1169,3557,3724,5097|17,0:2821,3483,3774,3808,3925,3938,4021,6781|18,0:413|19,0:236,439,698,1478,3913|20,0:912,963,1022,1230,1332,1612,1867,2428,3131,3685,4709,7254,7610,7655,7871|21,16:777,1191,1319,1342,1442,1638,2499|23,0:1327,1394,1715,1771,5520,6355,7538,8053|24,0:325|25,2:369,836,872,903,1228,1481,1608,2061,4918|26,0:4835,6162,7410,9670,9996,10289,10333,12655,12702,13939,17285|27,0:101,755,871,5685,8550|29,0:4564,6598,10069|30,0:459,1628,1967,3050,3301,3637,5862,8888,9150,11752,12987|31,0:382,681,1822,2810,2931|33,0:224|36,0:605,640|38,0:34,1900,1940,2517,2553,2690,2733,3490,3530,4144,4184,4765,4800,4834,4951,4994,5071,5161,5228,5396,5436,5497,5619,5674,5762,5834,5973,6021,6148,6269,6308,6516,6553,6573|39,0:1435,1499,1588,1957,2251,2420|40,0:360,593,785,1480,1803,3202,3588,3670,4396,4547,5285,5771,6762,6770,6824,6891,7008,7030,7531,8827,9030,9725,11267,11364,11599|41,0:1721,1749,2253,3135,3163,4150,4869,4967,5448,7360,7365,7656,7849|42,0:425,981,1456,6094,6123,6135,6915,8317,8358,8742,9269,9313,9343,9523,9741,9769,9790,9843,9894,10148,10520,10807,10833,12107,14408,14439,14479,14564,14675,14685,14885,14934,15023,15074,15170,15270,15296,15304,15440,15530,15565,15634,16897,16910,16947,16969,16991,17020,17033,17039,17451,17812,18088,18117,18130,18151,18367,18423|43,0:317|44,4:269,1448,2285,4269,5888,6361,7546,8125,8375,8469,8542,8637,8763,9724,11782,13703,13798,13847,14456,14672,15084,15912,16760,17154,17598,19824,19885,20474|46,0:158,389|47,0:1387,1771,2310|49,0:1598|50,0:221|51,0:433|52,0:2162,3621|53,0:2201|54,0:2480,2580,5287,7102,7144,7946,8506,8798,9147,9363,10254,10452,10563,12518,13776,14559,14577,17739,17879|56,0:629,1113,2546,2904,3408,3782,3805,4272,4277,4347,5537|57,0:58,958,3326,5655|59,16:2416,2504,2512,7103,9100,10944|60,0:658,2041|61,0:1575,1702,6179,6415,6502"/><wd nm="kage" rd="18,0:458"/><wd nm="kages" rd="44,0:14973"/><wd nm="kau" rd="23,16:6542"/><wd nm="kbid" rd="26,0:5769"/><wd nm="kbox" rd="8,0:629|23,0:1759"/><wd nm="kcs" rd="2,0:2581,6941,12122,15040,17670"/><wd nm="kdc" rd="54,0:4120"/><wd nm="kdir" rd="20,16:6049|57,0:7746"/><wd nm="kdw5nbguxhdaabgnvbaste0nvbxbsawfudevudgvychjpc2uxhdaa" rd="2,16:2853,7213,12394,15319,17951"/><wd nm="ke" rd="0,0:1922|2,0:19900|7,0:1498,3600|8,0:1958,4698,4916,8225,8865,9684|11,0:1973,3208|13,0:2056|14,0:2641,2885,3497|15,0:6018,6208|17,0:2405,3064,4392,6107,8590|19,0:56,3519,3821|20,0:4211,4383,5900|21,0:875,1338|23,0:2281,3320,4628,10186|25,0:1175|26,0:2102,4002,8282,11867,14435,15636|27,0:9041|29,0:2539,5082,8390|30,0:4273,5983,7312,7509,10728|36,0:203|40,0:1003,4507,5609,6966,10129|41,0:7860|42,0:3642,7022,8074,15536,17356|44,0:1969,3754,4383,10851,10899,18430,19818|45,0:836,1766|46,0:1660|49,0:1477|52,0:2461|54,0:2917|55,0:454|56,0:3836|57,0:2023,3869,4012,4320|59,0:1711,5714,5955|60,0:976|61,0:3686,3691,4402,7546|63,0:1314"/><wd nm="kecaqawfzelmakga1uebhmcvvmxczajbgnvbagtaknbmriweaydvqqhewltyw4gtwf0zw8xezarbgnvbaotckjsdwvkdw5nbguxhdaabgnvbaste0nvbxbsawfudevudgvychjpc2uxhdaa" rd="2,16:2853,7213,12394,15319,17951"/><wd nm="ked" rd="7,0:2333,2870|8,16:1120,7188,10732|14,0:2582,3736,5258|17,0:1099,7459,8234|38,0:153|40,0:3921,5386|42,0:6438,9851,14487,15031,15360|44,0:16116,19198|47,0:2274|49,0:1562|53,0:1277|54,0:12263|57,0:5629"/><wd nm="keep" rd="14,0:1908,2985|17,0:294,2729,5740|26,0:4831|30,0:116,9119|42,0:10824|47,0:2306|49,0:1594|57,0:3741,5019|59,0:9681"/><wd nm="keeping" rd="59,0:8580"/><wd nm="keeps" rd="54,0:5282"/><wd nm="kely" rd="18,0:1094|61,0:1685,4059"/><wd nm="ken" rd="8,0:8699|27,0:4472|44,0:16089|46,0:928|54,0:12134"/><wd nm="kend" rd="8,0:6705|15,16:6076"/><wd nm="kendaccess" rd="8,16:7164"/><wd nm="kens" rd="7,0:4842|8,0:5494"/><wd nm="kepassword" rd="2,0:4923,5070,9522,9674"/><wd nm="kept" rd="17,0:5791|42,0:5755"/><wd nm="ker" rd="42,0:10175"/><wd nm="kerberos" rd="54,0:2547,4125"/><wd nm="kes" rd="7,0:938,1746,2157|8,0:651,5013,9225|14,0:939|26,0:5618|30,0:13781|42,0:10755|44,0:14317,18806|52,0:6020"/><wd nm="ket" rd="20,0:3001"/><wd nm="kets" rd="6,0:306,339|26,0:12822"/><wd nm="key" rd="0,2:209,510,1288,1510,2933,3034,3427,3463,3573,3985,3998,4210,4469|1,0:588,632|5,0:837|6,0:87,184|8,0:7324|23,0:9435|40,0:8486|54,0:8023|57,0:1035,3225"/><wd nm="key_local_machine" rd="56,16:2439,3308,4638|60,16:1914"/><wd nm="keyalg" rd="2,16:2169,6189,11529,14329,17127"/><wd nm="keymanagement" rd="0,16:3904,4307,4403"/><wd nm="keymanage­ment" rd="0,16:3494,3708"/><wd nm="keypair" rd="2,16:2033,6053,11389,14186,16982"/><wd nm="keypass" rd="0,16:1620,3142,4321|2,16:2135,2294,3597,6155,6240,6378,6654,7954,8381,11493,11518,11817,11843,13160,13571,14035,14295,14461,14724,16118,16818,17093,17359,21098|23,16:8673,8680,9051,9374,9381,9740"/><wd nm="keypasswd" rd="0,16:1590,3114,4290|2,16:21025"/><wd nm="keys" rd="1,0:532|2,0:6391"/><wd nm="keystore" rd="0,16:66,569,1188,1209,1300,1694,1715,2310,2330,2835,2855,2945,3204,3223,3509,3896,3918,4010,4395,4417|1,2:371,401,488,900,1020,1095,1167,1225,1297,1365,1551,1635,1900,1969,2000,2146,2269,2336,2368|2,16:139,178,1443,1483,1606,1846,1957,2179,2329,3631,3694,3993,4535,4838,4888,5571,5977,6199,6268,6318,6362,6689,7988,8044,8415,8558,8592,9121,9428,9446,9487,10097,10467,10914,10982,11123,11231,11269,11316,11539,11553,11708,11854,11868,13171,13234,13582,13645,13906,13981,14013,14339,14358,14759,14778,16149,16200,16355,16386,16663,16781,16806,17137,17158,17393,17414,18737,18788,18943,18973,19204,19721,19734,19889,19924,20035,20195,20305,20386,20398,20540,20595,20656,20714,20729,20746,20756,20772,20841,21056,21068,21218,21233,21261,21430,21443|3,0:724,769|4,0:187,322,413|5,0:600|23,16:8691,8699,9025,9460,9531,9539,9589,9710,9864|29,16:1332|56,0:5380,5405,5486|57,0:2446,2956,3139|61,0:9751"/><wd nm="keystorefile" rd="2,0:4813,9403|57,0:2411,2514"/><wd nm="keystorepass" rd="2,0:4859,9458|57,0:2527,2883"/><wd nm="keystores" rd="0,0:378|1,0:97|2,0:6511,11602,14407,17207,19426|5,0:788"/><wd nm="keystoretype" rd="2,0:5093,9697|57,0:2543,3116"/><wd nm="keytool" rd="0,16:1115,1582,2762,3106,3835,4282|2,16:403,1974,2025,2269,3573,5994,6045,6466,6629,7930,8357,10861,11329,11381,11790,13125,13536,14127,14178,14692,16078,16923,16974,17325,18661,19629,20241,20341,20362,20516,20706,21017,21210|5,0:1079|6,1:9,45,77,224,411,437|23,16:8576,8623,8923|29,16:847,1274"/><wd nm="key­pass" rd="2,16:18703"/><wd nm="key­store" rd="0,0:927,999,2599,3786|2,16:13380,13792,19122,20802|4,0:209"/><wd nm="kflows" rd="44,0:12042"/><wd nm="kga1uebhmcvvmxczajbgnvbagtaknbmriweaydvqqhewltyw4gtwf0zw8xezarbgnvbaotckjsdwvkdw5nbguxhdaabgnvbaste0nvbxbsawfudevudgvychjpc2uxhdaa" rd="2,16:2853,7213,12394,15319,17951"/><wd nm="kground" rd="8,0:1498|54,0:11380"/><wd nm="kind" rd="8,0:877,8674|17,0:7703|27,0:10527,10781|29,0:1967|33,0:1093,1263|44,0:19214|54,0:16917|59,0:9003|61,0:4611"/><wd nm="kinds" rd="7,0:163|10,0:119|11,0:4928|12,0:3029,3573|25,0:251|26,0:164|30,0:2796|38,0:1675|44,0:12035,19534|54,0:15949"/><wd nm="king" rd="2,0:9357|7,0:1114|14,0:3187,4149|17,0:1442,7538|23,0:281|24,0:298|26,0:5278|27,0:7878|29,0:4246,6390|30,0:12015|31,2:225,308|40,2:759,1443,9228,9911,10793|41,0:163|42,4:1990,3540,8533,9081,14833,15726,16869|44,0:591,5957,15553,18783|47,0:1362,1744|51,0:406|54,0:5803,15573,15642|56,0:2313,3182,4512|59,0:1778,5772,6019|60,0:1788|61,0:10267"/></pk>